patron_ElioAmado_expoFP/__init__.py
patron_ElioAmado_expoFP/patron_ElioAmado_expoFP.py
patron_ElioAmado_expoFP-0.1.dist-info/METADATA
patron_ElioAmado_expoFP-0.1.dist-info/WHEEL
patron_ElioAmado_expoFP-0.1.dist-info/top_level.txt
patron_ElioAmado_expoFP-0.1.dist-info/RECORD
