Metadata-Version: 2.1
Name: patron_ElioAmado_expoFP
Version: 0.1
Summary: Print a pattern that can have 3 shapes
Author: Elio Amado Costa
Author-email: amadocosta5@gmail.com
